kepler_downloader_dr25/__init__.py
kepler_downloader_dr25/_version.py
kepler_downloader_dr25/downloader.py
kepler_downloader_dr25/filter.py
kepler_downloader_dr25/utils/__init__.py
kepler_downloader_dr25/utils/check_missing_kics.py
kepler_downloader_dr25/utils/generate_stats.py
kepler_downloader_dr25/utils/rebuild_database.py
kepler_downloader_dr25-1.5.0.dist-info/licenses/LICENSE
kepler_downloader_dr25-1.5.0.dist-info/METADATA
kepler_downloader_dr25-1.5.0.dist-info/WHEEL
kepler_downloader_dr25-1.5.0.dist-info/entry_points.txt
kepler_downloader_dr25-1.5.0.dist-info/top_level.txt
kepler_downloader_dr25-1.5.0.dist-info/RECORD
