Metadata-Version: 2.4
Name: kepler-downloader-dr25
Version: 1.5.0
Summary: A comprehensive toolkit for downloading and filtering Kepler DR25 FITS files from NASA's MAST archive
Home-page: https://github.com/akira921x/Kepler-Downloader-DR25
Author: akira921x
Author-email: akira921x <noreply@use-github-issues.com>
Maintainer-email: akira921x <noreply@use-github-issues.com>
License: Apache-2.0
Project-URL: Homepage, https://github.com/akira921x/Kepler-Downloader-DR25
Project-URL: Documentation, https://github.com/akira921x/Kepler-Downloader-DR25/blob/main/README.md
Project-URL: Repository, https://github.com/akira921x/Kepler-Downloader-DR25
Project-URL: Bug Reports, https://github.com/akira921x/Kepler-Downloader-DR25/issues
Keywords: kepler,nasa,astronomy,exoplanet,fits,mast,telescope,space,data,download
Classifier: Development Status :: 5 - Production/Stable
Classifier: Intended Audience :: Science/Research
Classifier: Topic :: Scientific/Engineering :: Astronomy
Classifier: License :: OSI Approved :: Apache Software License
Classifier: Programming Language :: Python :: 3
Classifier: Programming Language :: Python :: 3.10
Classifier: Programming Language :: Python :: 3.11
Classifier: Programming Language :: Python :: 3.12
Classifier: Programming Language :: Python :: 3.13
Classifier: Operating System :: OS Independent
Requires-Python: >=3.10
License-File: LICENSE
Requires-Dist: requests>=2.31.0
Requires-Dist: astroquery>=0.4.6
Requires-Dist: astropy>=5.0
Requires-Dist: pandas>=1.5.0
Requires-Dist: numpy>=1.21.0
Requires-Dist: tqdm>=4.65.0
Requires-Dist: redis>=4.5.0
Provides-Extra: dev
Requires-Dist: pytest>=7.0; extra == "dev"
Requires-Dist: pytest-cov>=4.0; extra == "dev"
Requires-Dist: black>=23.0; extra == "dev"
Requires-Dist: ruff>=0.1.0; extra == "dev"
Requires-Dist: mypy>=1.0; extra == "dev"
Requires-Dist: tox>=4.0; extra == "dev"
Requires-Dist: build>=0.10; extra == "dev"
Requires-Dist: twine>=4.0; extra == "dev"
Provides-Extra: test
Requires-Dist: pytest>=7.0; extra == "test"
Requires-Dist: pytest-cov>=4.0; extra == "test"
Requires-Dist: pytest-mock>=3.10; extra == "test"
Dynamic: author
Dynamic: home-page
Dynamic: license-file
Dynamic: requires-python
